scodia/__init__.py
scodia/plot_function_box.c
scodia/plot_function_box.cpython-312-x86_64-linux-gnu.so
scodia/plot_function_box.py
scodia/plot_function_ccidot.c
scodia/plot_function_ccidot.cpython-312-x86_64-linux-gnu.so
scodia/plot_function_ccidot.py
scodia/plot_function_cnv_heatmap.c
scodia/plot_function_cnv_heatmap.cpython-312-x86_64-linux-gnu.so
scodia/plot_function_cnv_heatmap.py
scodia/plot_function_deg.c
scodia/plot_function_deg.cpython-312-x86_64-linux-gnu.so
scodia/plot_function_deg.py
scodia/plot_function_gsea.c
scodia/plot_function_gsea.cpython-312-x86_64-linux-gnu.so
scodia/plot_function_gsea.py
scodia/plot_function_marker.c
scodia/plot_function_marker.cpython-312-x86_64-linux-gnu.so
scodia/plot_function_marker.py
scodia/plot_function_stackedbar.c
scodia/plot_function_stackedbar.cpython-312-x86_64-linux-gnu.so
scodia/plot_function_stackedbar.py
scodia/plot_function_umap.c
scodia/plot_function_umap.cpython-312-x86_64-linux-gnu.so
scodia/plot_function_umap.py
scodia/plot_function_violin.c
scodia/plot_function_violin.cpython-312-x86_64-linux-gnu.so
scodia/plot_function_violin.py
scodia/scodia_main.c
scodia/scodia_main.cpython-312-x86_64-linux-gnu.so
scodia/scodia_main.py
scodia/scodia_supp.py
scodia/tool_map.c
scodia/tool_map.cpython-312-x86_64-linux-gnu.so
scodia/tool_map.py
mlbi_scodia-0.0.6.dist-info/METADATA
mlbi_scodia-0.0.6.dist-info/WHEEL
mlbi_scodia-0.0.6.dist-info/entry_points.txt
mlbi_scodia-0.0.6.dist-info/top_level.txt
mlbi_scodia-0.0.6.dist-info/RECORD
mlbi_scodia-0.0.6.dist-info/licenses/LICENSE
